build_diagnostics-1.5.0.dist-info/licenses/LICENSE
diagnostics/__init__.py
diagnostics/diagnostics.py
build_diagnostics-1.5.0.dist-info/METADATA
build_diagnostics-1.5.0.dist-info/WHEEL
build_diagnostics-1.5.0.dist-info/top_level.txt
build_diagnostics-1.5.0.dist-info/RECORD
