Metadata-Version: 2.4
Name: build-diagnostics
Version: 1.5.0
Summary: A package to retrieve build files for diagnostics and log them in a server
Author-email: Leetbob <leetbob@gmail.com>
License-Expression: MIT
Classifier: Programming Language :: Python :: 3
Classifier: Operating System :: OS Independent
Requires-Python: >=3.9
License-File: LICENSE
Dynamic: license-file
